{
  "slug": "libra-may-2026",
  "seo_title": "Libra May 2026 Horoscope: Key Dates, Love, Career & Crystal of the Month",
  "h1": "Libra May 2026 Horoscope and Crystal of the Month",
  "month": "May",
  "year": 2026,
  "sign": "Libra",
  "sign_element": "Air",
  "ruling_planet": "Venus",
  "energy_theme": "Money, intimacy, and meaning in three moons",
  "crystal_of_month": "Pyrite",
  "alt_crystals": [
    "Citrine",
    "Rose Quartz"
  ],
  "lucky_colors": [
    "Emerald",
    "Soft gold"
  ],
  "lucky_number": 4,
  "affirmation": "I hold my value even in deep waters",
  "at_a_glance": {
    "Energy Theme": "Income clarity, intimacy reset, and a meaning-Blood-Moon",
    "Key Dates": "Full Moon May 3 (Scorpio, 2nd house) / New Moon May 16 (Taurus, 8th house) / Blue Moon May 31 (Sagittarius, 3rd house)",
    "Love": "Intimacy deepens through honest money and sex conversations",
    "Career": "A pricing or income decision reaches clarity",
    "Crystal of the Month": "Pyrite",
    "Lucky Colors": "Emerald, soft gold",
    "Lucky Number": 4,
    "Affirmation": "I hold my value even in deep waters"
  },
  "content": "<h2>This Month's Energy</h2>\n\nLibra, May 2026 takes you deep. The Scorpio Full Moon on May 3 lights your second house of income and self-worth — a pricing, salary, or self-value decision reaches clarity. The Taurus New Moon on May 16 falls in your eighth house of intimacy, shared resources, and psychological depth — your annual reset for emotional and financial honesty. The Blue Moon on May 31 lands in your third house of communication and writing — a writing project, conversation, or sibling matter reaches a small climax as the month closes. Abundance and expansion is the theme, but for you the abundance comes only after you tell a deep truth about what you are worth — in money and in love.\n\n<h2>Key Dates for Libra in May 2026</h2>\n\n| Date | Transit | Meaning for Libra | Do / Avoid |\n|------|---------|-------------------|------------|\n| May 3 | Full Moon in Scorpio (Flower Moon) | Income, self-worth, possessions — Do: make the pricing decision you have been delaying / Avoid: underpricing to avoid conflict |\n| May 9 | Venus square Pluto | Power in love or money — Do: name the dynamic / Avoid: manipulating around it |\n| May 16 | New Moon in Taurus | Intimacy, shared resources, psychological reset — Do: tell one financial or sexual truth you have been holding / Avoid: avoiding the depth conversation |\n| May 20 | Sun enters Gemini | Travel, learning, expansion — Do: book the trip or start the course / Avoid: staying small |\n| May 25 | Mars enters Virgo | Quiet behind-the-scenes work — Do: plan, rest, and research / Avoid: launching publicly |\n| May 31 | Blue Moon in Sagittarius (Micro) | Communication, writing, siblings — Do: ship the writing, have the sibling conversation / Avoid: endlessly editing |\n\n<h2>Career & Money</h2>\n\nLibra, the Scorpio Full Moon on May 3 in your second house is your most important pricing clarity of the spring — a salary negotiation, contract renewal, or rate decision reaches a clear yes-or-no. Get your numbers in order before May 3, send the message in the first ten days of the month, and quote the higher number; the Libra trap is to wait for harmony that the moment does not actually require. The Taurus New Moon on May 16 in your eighth house is your annual shared-resources reset — a tax, debt, investment, or jointly-held-money conversation, sometimes an inheritance or settlement, sometimes a partner's financial truth finally coming into the open. From May 20 the Sun in Gemini opens a travel and learning window that helps you step back from the intensity and see the bigger picture. When Mars enters Virgo on May 25 you enter a quieter, behind-the-scenes work cycle; do not launch publicly in the final week of May — plan, rest, and research. The Blue Moon on May 31 in your communication house can bring a writing or sibling matter to a clear close; the email you have been editing for three weeks needs to be sent. Pair the money reset with our <a href=\"/crystals-for-wealth/\">crystals for wealth</a> framework.\n\n<h2>Love & Relationships</h2>\n\nThe Taurus New Moon on May 16 in your eighth house is your most intimate relationship window of the year — depth, vulnerability, shared money, shared body. Single Libra may meet someone whose chemistry feels instantly deep, often through a shared financial or psychological chapter; partnered Libra will be asked to tell a financial or sexual truth they have been sidestepping. The Venus-Pluto square on May 9 is not a fight to win but a pattern to see — notice whether the love-and-money dynamic mirrors one you learned early in your family of origin, and name it once rather than weaponizing it for a year. The Blue Moon on May 31 in your third house brings a sibling, neighbor, or short-form communication into focus; the conversation you have been avoiding needs to happen, and the words you have been polishing in your head need to be spoken aloud. The key for Libra in May is honest depth over performed harmony — the partnership that holds under that pressure is the one to keep. For support in softening defenses and speaking honestly in love, see our <a href=\"/crystals-for-love/\">crystals for love</a> collection.\n\n<h2>Health & Wellness</h2>\n\nThe second-house Scorpio Full Moon on May 3 makes early May a throat-and-neck check-in — hydrate, warm drinks, gentle stretching. The eighth-house Taurus New Moon on May 16 is a true psychological reset; treat the third week of May as a fasting-from-noise week. Pyrite is traditionally associated with vitality, confidence, and an energized will — often used as a desk companion during periods when self-worth and money are being renegotiated. Walk in nature, eat real food, sleep well — the basics are the medicine this month. The second-house Scorpio Full Moon on May 3 makes early May a throat-and-neck check-in — hydrate, warm drinks, gentle stretching, and notice whether you are swallowing words you should be speaking. The eighth-house Taurus New Moon on May 16 is a true psychological reset; treat the third week of May as a fasting-from-noise week with minimal social media and maximal time in nature. Walk, eat real food, sleep well — the basics are the medicine this month.\n\n<h2>Crystal of the Month: Pyrite</h2>\n\n<strong>Why this crystal fits Libra this month.</strong> Libra, your grace is famous; May asks for the unshakeable self-worth that lets that grace hold under pressure. Pyrite, traditionally associated with confidence, willpower, and value, lines up directly with the Scorpio Full Moon in your income house and the Taurus New Moon in your shared-resources house. It is the stone that helps you say <em>this is what I am worth</em> without flinching.\n\n<strong>How to use it during May.</strong> Hold Pyrite on May 3 when you make the pricing decision. Carry it on May 16 when you have the intimacy or shared-money conversation. Keep it on your desk through the month as a steady value-reminder.\n\n<strong>Best date to use it.</strong> May 3, the Scorpio Full Moon in your second house — with Pyrite in hand, write the real number you are worth and the message that asks for it.\n\n<strong>Read more.</strong> Deep dive in our full <a href=\"/gemstone/pyrite-meaning/\">Pyrite meaning guide</a> and explore the complete <a href=\"/libra-crystals/\">Libra crystals</a> collection.\n\n<h2>Monthly Crystal Ritual</h2>\n\n<strong>Date:</strong> May 16, Taurus New Moon (eighth house of intimacy and shared resources).\n\n1. Cleanse your Pyrite with sound or brief sunlight (five minutes, not midday).\n2. Write the answer to one question: <em>What is one financial or sexual truth I have not said aloud?</em> Write the real answer.\n3. Because the Scorpio Full Moon two weeks earlier was about income, write a second line: <em>The income number I am claiming by November is ___.</em>\n4. Place the Pyrite on both lines overnight. The next morning, take one small action — send the message, schedule the conversation, write the email — that moves either line forward.\n\n<h2>Shop</h2>\n\n<em>Want to build your monthly crystal toolkit? Explore the full <a href=\"/libra-crystals/\">Libra crystal guide</a> for stones traditionally connected with love, value, and clear communication — Pyrite pairs beautifully with Rose Quartz for a Libra worth-and-love kit.</em>\n\n<h2>FAQ</h2>\n\n<strong>What should Libra avoid in May 2026?</strong>\nAvoid waiting for harmony before sending the pricing message on May 3. The Scorpio Full Moon in your income house rewards the ask made clearly, not the ask softened to preserve comfort. Also avoid weaponizing the Pluto dynamic on May 9 — name the pattern once, kindly, then act.\n\n<strong>Is May 2026 a good month for Libra?</strong>\nYes — especially for money and intimacy. The May 3 Scorpio Full Moon in your income house and the May 16 Taurus New Moon in your intimacy house are both standout days.\n\n<strong>What does the May 3 Scorpio Full Moon mean for Libra?</strong>\nIt activates your second house of income and self-worth. A pricing, salary, or self-value decision reaches clarity in the first week of May.\n\n<strong>How will the May 16 Taurus New Moon affect Libra?</strong>\nIt activates your eighth house of intimacy, shared resources, and psychological depth. Tell one financial or sexual truth you have been holding.\n\n<strong>What is the best crystal for Libra in May 2026?</strong>\nPyrite. With an income Full Moon and an intimacy New Moon, unshakeable self-worth is the work — and Pyrite is the traditional value-and-willpower ally.\n\n<strong>Libra-only question: Should I have the money conversation with my partner in May 2026?</strong>\nYes. The Taurus New Moon in your eighth house on May 16 is one of your clearest shared-finances windows of the year. Prepare your numbers before May 9, have the conversation in the week of May 16–22.\n\n<h2>Related</h2>\n\n<ul>\n<li><a href=\"/libra-2026/\">Libra 2026 Yearly Horoscope</a></li>\n<li><a href=\"/libra-crystals/\">Libra Crystals</a></li>\n<li><a href=\"/libra/\">Libra Sign Guide</a></li>\n<li>Monthly horoscope hub: <a href=\"/category/zodiac/horoscope/\">/category/zodiac/horoscope/</a></li>\n</ul>\n<script type=\"application/ld+json\">\n{\n  \"@context\": \"https://schema.org\",\n  \"@type\": \"FAQPage\",\n  \"mainEntity\": [\n    {\n      \"@type\": \"Question\",\n      \"name\": \"What should Libra avoid in May 2026?\",\n      \"acceptedAnswer\": {\n        \"@type\": \"Answer\",\n        \"text\": \"Is May 2026 a good month for Libra?\\nYes — especially for money and intimacy. The May 3 Scorpio Full Moon in your income house and the May 16 Taurus New Moon in your intimacy house are both standout days.\"\n      }\n    },\n    {\n      \"@type\": \"Question\",\n      \"name\": \"What does the May 3 Scorpio Full Moon mean for Libra?\",\n      \"acceptedAnswer\": {\n        \"@type\": \"Answer\",\n        \"text\": \"How will the May 16 Taurus New Moon affect Libra?\\nIt activates your eighth house of intimacy, shared resources, and psychological depth. Tell one financial or sexual truth you have been holding.\"\n      }\n    },\n    {\n      \"@type\": \"Question\",\n      \"name\": \"What is the best crystal for Libra in May 2026?\",\n      \"acceptedAnswer\": {\n        \"@type\": \"Answer\",\n        \"text\": \"Libra-only question: Should I have the money conversation with my partner in May 2026?\\nYes. The Taurus New Moon in your eighth house on May 16 is one of your clearest shared-finances windows of the year. Prepare your numbers before May 9, have the conversation in the week of May 16–22.\"\n      }\n    }\n  ]\n}\n</script>\n\n\n<em>Review: <a href=\"/libra-april-2026/\">Libra April 2026 Horoscope</a> · Preview: <a href=\"/libra-june-2026/\">Libra June 2026 Horoscope</a> · Year view: <a href=\"/libra-2026/\">Libra 2026 Yearly Horoscope</a></em>\n\n<hr>\n\n<em>Astrology and crystal meanings are offered for entertainment, reflection, and spiritual inspiration. Crystals are traditionally associated with certain symbolic qualities, but they are not a substitute for medical, financial, or professional advice. All stones are genuine, ethically sourced, and real — not dyed, not glass.</em>",
  "images": {
    "featured": {
      "file": "assets/images/generated/8.zodiac-monthly-horoscope/libra-may-2026/libra-may-2026-featured.webp",
      "source_type": "scene",
      "alt": "Libra May 2026 monthly horoscope with Pyrite as crystal of the month, zodiac symbol ♎",
      "prompt": "An editorial flat-lay for Libra May horoscope: a Pyrite crystal resting on natural linen beside a subtle zodiac symbol ♎, with elements evoking lush spring with abundant flowers and warm sunshine, soft pink, ivory and pale blue tones, soft natural light, representing Abundance and expansion, no text, no watermark, no human face"
    },
    "crystal_month": {
      "file": "assets/images/generated/8.zodiac-monthly-horoscope/libra-may-2026/libra-may-2026-crystal-month.webp",
      "source_type": "closeup",
      "alt": "Pyrite crystal of the month for Libra May 2026 horoscope",
      "prompt": "A macro close-up photograph of a Pyrite crystal showing fine surface texture and natural beauty, soft even studio light, soft pink, ivory and pale blue background, editorial gemstone guide quality, representing the monthly anchor stone for Libra in May, no text, no watermark"
    },
    "ritual": {
      "file": "assets/images/generated/8.zodiac-monthly-horoscope/libra-may-2026/libra-may-2026-ritual.webp",
      "source_type": "lifestyle",
      "alt": "Monthly crystal ritual for Libra May 2026 using Pyrite",
      "prompt": "A serene lifestyle scene: a Pyrite crystal placed on a wooden surface with a journal, a candle, and seasonal elements evoking lush spring with abundant flowers and warm sunshine, representing a new moon or full moon crystal ritual, warm natural daylight, soft pink, ivory and pale blue accents, minimalist wellness aesthetic, no text, no watermark, no human face"
    }
  }
}