{
  "title": "Most Faked Crystals: 10 Stones Often Sold Fake (2026 Guide)",
  "slug": "most-faked-crystals",
  "url": "/blog/most-faked-crystals/",
  "subject_label": "Crystals",
  "h1": "Most Faked Crystals: 10 Stones Often Sold Fake",
  "primary_kw": "most faked crystals",
  "secondary_kw": [
    "fake crystals list",
    "crystals that are commonly faked",
    "how to spot fake turquoise",
    "fake moldavite",
    "fake citrine"
  ],
  "word_target": 2700,
  "quality_tier": "hub",
  "methods_used": [
    "naming",
    "price",
    "bubbles",
    "color_banding",
    "specific_gravity",
    "hardness",
    "uv_light"
  ],
  "stone_cases": [
    "amethyst",
    "citrine",
    "turquoise",
    "lapis_lazuli",
    "moldavite",
    "malachite",
    "jadeite",
    "obsidian",
    "clear_quartz",
    "rose_quartz"
  ],
  "author": {
    "name": "Earthward Editorial Team",
    "byline": "Earthward's crystal care and sourcing team",
    "reviewed_by": "Earthward's mineral-sourcing reviewers"
  },
  "date_modified": "2026-06-28",
  "date_published": "2026-06-28",
  "faq_picks": {
    "intent": [
      "Which crystals are most commonly faked?",
      "How can you tell if a crystal is fake?",
      "What is the most faked crystal?",
      "Is fake turquoise common?"
    ],
    "conversion": [
      "Where can I buy genuine crystals that are not fake?",
      "How much do real crystals cost vs fakes?",
      "Are lab-created crystals considered fake?"
    ],
    "trust": [
      "Are fake crystals dangerous?",
      "Can home tests spot all fakes?"
    ],
    "selective": [
      "Why is moldavite so often faked?",
      "Is dyed howlite always sold as turquoise?"
    ]
  },
  "buying_guide": {
    "shop_cta_target": "/product-category/healing-crystals-jewelry/",
    "shop_cta_anchor": "Browse genuine crystal jewelry"
  },
  "internal_links": {
    "meaning_min": 3,
    "flagship": {
      "anchor": "How to Tell If a Crystal Is Real",
      "url": "/blog/how-to-tell-if-crystal-is-real/"
    },
    "amethyst_deep": {
      "anchor": "Real vs Fake Amethyst (deep dive)",
      "url": "/blog/real-vs-fake-amethyst/"
    },
    "clear_quartz_deep": {
      "anchor": "How to Tell If Clear Quartz Is Real (deep dive)",
      "url": "/blog/how-to-tell-if-clear-quartz-is-real/"
    }
  },
  "schema": {
    "types": [
      "Article",
      "FAQPage",
      "BreadcrumbList"
    ],
    "howto_name": "How to Spot the Most Faked Crystals",
    "howto_total_time": "PT20M",
    "howto_steps": [
      {
        "step": 1,
        "name": "Learn the most-faked list",
        "text": "Amethyst, citrine, turquoise, lapis, moldavite, malachite, jadeite, obsidian, clear quartz, rose quartz lead the fake market."
      },
      {
        "step": 2,
        "name": "Apply the species-specific test",
        "text": "Each stone has one headline signal (turquoise: matrix, lapis: pyrite flecks, jadeite: heft, moldavite: origin)."
      },
      {
        "step": 3,
        "name": "Cross-check price and naming",
        "text": "Bargain pricing on high-value species (jadeite, moldavite, large turquoise) is the strongest pre-purchase warning."
      },
      {
        "step": 4,
        "name": "Use a 10x loupe for any transparent stone",
        "text": "Bubbles separate glass from natural quartz-family stones."
      },
      {
        "step": 5,
        "name": "For valuable pieces, get a lab certificate",
        "text": "Jadeite, moldavite, and large turquoise warrant professional certification."
      }
    ]
  },
  "compliance": {
    "avoid": [
      "100% genuine",
      "100% authentic",
      "guaranteed real",
      "verified authentic",
      "always works",
      "never fails",
      "the only way to know",
      "fake crystals are dangerous"
    ],
    "gentle_note": "This guide covers the stones most often sold as imitations. Home tests help you spot common fakes, but for valuable specimens (jadeite, moldavite, untreated turquoise), a gemological lab report is the gold standard. Crystal meanings and energetic properties are separate from authenticity.",
    "brand_tagline": "We name our stones and sources — return to what's real.",
    "ai_banned_words": [
      "delve",
      "tapestry",
      "realm",
      "unlock your potential",
      "manifest abundance",
      "elevate your vibration"
    ]
  },
  "three_perspectives": {
    "science": "55%",
    "spirituality": "25%",
    "psychology": "20%"
  },
  "image_plan": {
    "hero": {
      "size": "1536x864",
      "scene": "collection of 10 most-faked crystals arranged with labels",
      "filename": "most-faked-crystals-hero.jpg"
    },
    "comparison": {
      "size": "1200x800",
      "scene": "genuine turquoise with matrix vs dyed howlite side by side",
      "filename": "most-faked-crystals-turquoise.jpg"
    },
    "test_diagram": {
      "size": "1200x800",
      "scene": "genuine lapis with pyrite flecks vs fake uniform blue side by side",
      "filename": "most-faked-crystals-lapis.jpg"
    }
  },
  "rank_math_title": "Most Faked Crystals: 10 Stones Often Sold Fake (2026 Guide)",
  "rank_math_description": "Most faked crystals: 10 stones often sold fake, including turquoise, amethyst, citrine, moldavite, lapis, and jadeite. Each with mineral data (Mohs, SG, formula) from GIA and mindat, and the one test that catches the fake. Updated 2026.",
  "rank_math_focus_keyword": "most faked crystals",
  "excerpt": "The ten crystals most commonly sold as fakes — turquoise, amethyst, moldavite, lapis, jadeite, and more — with mineral data and the one headline test that catches each imitation.",
  "faq_schema": [
    {
      "question": "Which crystals are most commonly faked?",
      "answer_placeholder": "{{AI_FAQ_0}}",
      "category": "intent"
    },
    {
      "question": "How can you tell if a crystal is fake?",
      "answer_placeholder": "{{AI_FAQ_1}}",
      "category": "intent"
    },
    {
      "question": "What is the most faked crystal?",
      "answer_placeholder": "{{AI_FAQ_2}}",
      "category": "intent"
    },
    {
      "question": "Is fake turquoise common?",
      "answer_placeholder": "{{AI_FAQ_3}}",
      "category": "intent"
    },
    {
      "question": "Where can I buy genuine crystals that are not fake?",
      "answer_placeholder": "{{AI_FAQ_4}}",
      "category": "conversion"
    },
    {
      "question": "How much do real crystals cost vs fakes?",
      "answer_placeholder": "{{AI_FAQ_5}}",
      "category": "conversion"
    },
    {
      "question": "Are lab-created crystals considered fake?",
      "answer_placeholder": "{{AI_FAQ_6}}",
      "category": "conversion"
    },
    {
      "question": "Are fake crystals dangerous?",
      "answer_placeholder": "{{AI_FAQ_7}}",
      "category": "trust"
    },
    {
      "question": "Can home tests spot all fakes?",
      "answer_placeholder": "{{AI_FAQ_8}}",
      "category": "trust"
    },
    {
      "question": "Why is moldavite so often faked?",
      "answer_placeholder": "{{AI_FAQ_9}}",
      "category": "selective"
    },
    {
      "question": "Is dyed howlite always sold as turquoise?",
      "answer_placeholder": "{{AI_FAQ_10}}",
      "category": "selective"
    }
  ],
  "howto_schema": {
    "name": "How to Spot the Most Faked Crystals",
    "totalTime": "PT20M",
    "steps": [
      {
        "step": 1,
        "name": "Learn the most-faked list",
        "text": "Amethyst, citrine, turquoise, lapis, moldavite, malachite, jadeite, obsidian, clear quartz, rose quartz lead the fake market."
      },
      {
        "step": 2,
        "name": "Apply the species-specific test",
        "text": "Each stone has one headline signal (turquoise: matrix, lapis: pyrite flecks, jadeite: heft, moldavite: origin)."
      },
      {
        "step": 3,
        "name": "Cross-check price and naming",
        "text": "Bargain pricing on high-value species (jadeite, moldavite, large turquoise) is the strongest pre-purchase warning."
      },
      {
        "step": 4,
        "name": "Use a 10x loupe for any transparent stone",
        "text": "Bubbles separate glass from natural quartz-family stones."
      },
      {
        "step": 5,
        "name": "For valuable pieces, get a lab certificate",
        "text": "Jadeite, moldavite, and large turquoise warrant professional certification."
      }
    ],
    "supplies": [
      "10x jeweler's loupe",
      "365nm UV flashlight (optional)",
      "Reference glass object for heft comparison"
    ],
    "tools": []
  },
  "diffHints": {
    "subject_scope": "collection-10-stones",
    "methods_count": 7,
    "stone_cases_count": 10,
    "crystal_vs_glass": false,
    "m4_mode": "multi_overview"
  },
  "content": "<p class=\"article-byline\"><em>By Earthward Editorial Team · Earthward's crystal care and sourcing team · Updated 2026-06-28 · Reviewed by Earthward's mineral-sourcing reviewers</em></p>\n<p>Some crystals are faked far more often than others — and knowing which ones, and how each is typically imitated, is the single most useful skill a buyer can build. This guide covers the ten crystals most commonly sold as fakes, with the mineral data and the one headline test that catches each imitation. If a stone you are considering is on this list, read its section before you buy.</p>\n\n<h2>Quick Answer: How to Tell If a Crystals Is Real</h2>\n<p>The fakes cluster around a predictable set of stones: those that are popular, expensive enough to make substitution profitable, or visually easy to copy in glass, plastic, or dyed alternatives. For each of the ten stones below, there is one test that catches most fakes — the matrix test for turquoise, the pyrite-fleck test for lapis, the heft test for jadeite, the origin test for moldavite. The general tests from the full guide (bubbles, temperature, hardness, price, naming) apply across all of them.</p>\n<p>The three most reliable at-home tests to start with:</p>\n<ul>\n<li>Naming and price — read the listing first. Vague names (\"purple crystal,\" \"energy stone\") and prices far below the species' market range are the strongest pre-purchase warnings.</li>\n<li>Bubbles under a loupe — for any transparent stone on this list (amethyst, citrine, clear quartz, rose quartz), round bubbles mean glass.</li>\n<li>Species-specific tests — each stone has one headline signal (turquoise: matrix, lapis: pyrite, jadeite: heft, malachite: banding). Learn the one that matters for the stone you want.</li>\n</ul>\n<p><em>No single home test is 100% conclusive — these tests work together. For valuable specimens, a gemological lab report is the gold standard.</em></p>\n\n<h2>Why Fake Crystals Are So Common</h2>\n<p>The fake-crystal market is not random — it concentrates where the economics favor substitution. A stone gets heavily faked when three conditions line up: it is popular enough that demand outpaces ethical supply, it is expensive enough (or its high grades are expensive enough) that substitution is profitable, and its appearance can be approximated by glass, plastic, dye, or a cheaper mineral. The ten stones below meet all three conditions. Together they account for the great majority of fakes a buyer will encounter.</p>\n<p>The fakes follow recognizable patterns. Glass imitations dominate for transparent stones (amethyst, citrine, clear quartz, rose quartz) — dyed to match the color, often with round bubbles visible under a loupe. Plastic and resin fakes appear in opaque stones sold as cheap beads (turquoise, malachite, lapis). Dyed stones substitute a cheap mineral for an expensive one: howlite dyed blue for turquoise, jasper dyed for lapis, low-grade quartz dyed for jade. Lab-grown (synthetic) quartz is chemically genuine but factory-made. And for rare stones like moldavite, plain green bottle glass is the most common imitation, relying on buyers who do not know the origin story.</p>\n<p>Each stone has a specific weakness that fakes exploit and a specific test that catches the fake. Turquoise's weakness is that dyed howlite copies its color; its test is the natural matrix. Lapis's weakness is that dyed jasper copies its blue; its test is the pyrite flecks. Jadeite's weakness is its high value, inviting quartz and serpentine substitutes; its test is the density. Moldavite's weakness is its rarity and high price; its test is the Czech-only origin. The general tests from the full guide apply everywhere, but the species-specific tests are what catch the sophisticated fakes for each stone.</p>\n\n<h2>How Fakes Are Made (and the Tests That Catch Them)</h2>\n<p>Before the stone-by-stone breakdown, here is how the most common fakes are made and the general tests that catch them. The seven methods below apply across all ten stones; each stone's section then adds the one test specific to that species. The mineral data table that follows gives you the numbers — Mohs hardness, specific gravity, refractive index — to verify what the tests suggest.</p><h3>🏷️ Test 10: Naming & Source Transparency</h3>\n<p><strong>The science behind it:</strong> Reputable sellers identify stones by their proper mineral name and origin, because mineral species and locality affect value and care. Vague or misleading names are a marketing red flag: the glass industry calls leaded glass \"crystal\" (lead crystal, crystal glass), so \"crystal quartz\" can mean glass rather than natural quartz. Sellers who hide behind \"mystery stone,\" \"energy crystal,\" or omit locality are harder to hold accountable.</p>\n<p><strong>Real vs fake at a glance:</strong></p>\n<table>\n<thead><tr><th>Signal</th><th>Genuine</th><th>Fake (glass / plastic)</th></tr></thead>\n<tbody>\n<tr><td>Stone name on listing</td><td>Proper mineral name (Natural Amethyst, SiO₂)</td><td>Vague (\"purple crystal,\" \"energy stone\") or industry code (\"crystal quartz\" = glass)</td></tr>\n<tr><td>Treatment disclosure</td><td>Disclosed (heat-treated citrine, lab-created)</td><td>Hidden or denied</td></tr>\n<tr><td>Locality</td><td>Specific origin (Brazil, Uruguay, Zambia)</td><td>Generic (\"imported,\" none listed)</td></tr>\n</tbody>\n</table>\n<p><strong>How to do it:</strong></p>\n<ol>\n<li>Read the listing carefully — does it name the actual mineral species, or use vague marketing terms?</li>\n<li>Check for treatment disclosure: reputable sellers note heat treatment, irradiation, dyeing, or lab creation.</li>\n<li>Look for locality information — specific origins (Brazil for amethyst, Madagascar for labradorite) signal a seller who knows their stock.</li>\n</ol>\n<p><strong>Limitations:</strong> A seller who names stones correctly can still sell glass; and a small honest seller may omit locality without ill intent. Naming transparency is a positive signal but not proof. Conversely, vague naming is a warning, not a verdict. Use it to decide which sellers warrant deeper trust, combined with the other tests.</p>\n<p><strong>Best stones for this test:</strong> All stones, especially when buying online sight-unseen. The single most useful pre-purchase signal.</p>\n<p><em>Source: GIA / FTC guidelines on gemstone disclosure.</em></p><h3>💰 Test 9: Price Red Flag</h3>\n<p><strong>The science behind it:</strong> Genuine natural crystals carry real costs: mining, sorting, cutting, polishing, transport, and the reality that high-quality specimens are finite. A price far below the established market range signals that something is off — either synthetic, glass, dyed, or reconstituted material being sold as natural. While promotions exist, a consistent dramatic discount across a seller's entire catalog is a structural red flag, not a sale.</p>\n<p><strong>Real vs fake at a glance:</strong></p>\n<table>\n<thead><tr><th>Signal</th><th>Genuine</th><th>Fake (glass / plastic)</th></tr></thead>\n<tbody>\n<tr><td>Price vs. market range</td><td>Within reasonable market range for the species and quality</td><td>Far below market (often 50-80% cheaper)</td></tr>\n<tr><td>Consistency of discount</td><td>Occasional promotions on specific pieces</td><td>Entire catalog suspiciously cheap</td></tr>\n<tr><td>Quality claims vs. price</td><td>Price matches claimed grade</td><td>\"Museum quality\" at bargain prices</td></tr>\n</tbody>\n</table>\n<p><strong>How to do it:</strong></p>\n<ol>\n<li>Compare the seller's prices against established reference points (gemological market guides, reputable dealers).</li>\n<li>Be wary of \"too good to be true\" pricing — a large natural amethyst geode for the price of a tumbled stone is not a deal, it is a different material.</li>\n<li>Use price as one signal among many — a fair price does not guarantee authenticity, but a wildly low price is a strong warning.</li>\n</ol>\n<p><strong>Limitations:</strong> Price alone never confirms authenticity — a seller can charge full price for glass. And genuine inexpensive stones exist (clear quartz, common agate, rose quartz rough are legitimately affordable). Use price as an auxiliary signal: a red flag warrants deeper testing, but a reasonable price does not exempt a stone from the other tests.</p>\n<p><strong>Best stones for this test:</strong> All stones, as an auxiliary signal — especially high-value species (jadeite, moldavite, large amethyst geodes, tanzanite) where prices are well-established and dramatic discounts are implausible.</p>\n<p><em>Source: market reference — gemological pricing guides.</em></p><h3>🔍 Test 4: Bubble Inspection (10x Loupe)</h3>\n<p><strong>The science behind it:</strong> Manufactured glass traps small spherical or teardrop-shaped air bubbles as it cools — a tell-tale sign of industrial origin. Natural minerals form over geological time and instead contain natural inclusions: needle-like rutile, two-phase gas-liquid inclusions, mineral crystals, or \"fingerprints\" of healed fractures. A 10x jeweler's loupe reveals the difference: round bubbles mean glass; irregular inclusions mean natural.</p>\n<p><strong>Real vs fake at a glance:</strong></p>\n<table>\n<thead><tr><th>Signal</th><th>Genuine</th><th>Fake (glass / plastic)</th></tr></thead>\n<tbody>\n<tr><td>Under 10x loupe</td><td>Needle/plate inclusions, growth lines, mineral flecks</td><td>Perfectly round bubbles, swirls, no irregular inclusions</td></tr>\n<tr><td>Bubble shape</td><td>None (natural minerals rarely trap air)</td><td>Spherical or teardrop bubbles</td></tr>\n<tr><td>Internal texture</td><td>Chaotic, asymmetric, \"natural\"</td><td>Too clean, or with flow lines from manufacturing</td></tr>\n</tbody>\n</table>\n<p><strong>How to do it:</strong></p>\n<ol>\n<li>Use a 10x jeweler's loupe (an inexpensive tool — about $10-15 online).</li>\n<li>Hold the stone against a light source (window or lamp) and look through it with the loupe.</li>\n<li>Scan for perfectly round, spherical bubbles — these are characteristic of glass. Natural stones show irregular inclusions instead.</li>\n</ol>\n<p><strong>Limitations:</strong> High-quality optical glass and fused quartz can be manufactured bubble-free, so the absence of bubbles does not guarantee natural origin — but the presence of round bubbles almost always indicates glass. Some natural stones (like enhydro quartz) do contain moving water bubbles, but these are elongated or angular, not perfectly round. Requires a loupe; the naked eye usually cannot resolve the smallest bubbles.</p>\n<p><strong>Best stones for this test:</strong> Transparent stones sold as clear quartz, citrine, topaz, or diamond simulants. Less useful for opaque stones where you cannot see inside.</p>\n<p><em>Source: GIA Gem Reference Guide — inclusions in natural vs. synthetic; mindat.org.</em></p><h3>🌈 Test 5: Color Banding & Zoning</h3>\n<p><strong>The science behind it:</strong> Natural color in minerals forms unevenly because crystal growth happens over geological time under changing conditions. Genuine amethyst shows subtle color zoning — deeper purple at the tips, lighter near the base, with natural gradation. Synthetic quartz grown in a lab colors uniformly and looks \"flat\" or overly saturated. Dyed stones concentrate pigment in surface cracks and fissures rather than throughout.</p>\n<p><strong>Real vs fake at a glance:</strong></p>\n<table>\n<thead><tr><th>Signal</th><th>Genuine</th><th>Fake (glass / plastic)</th></tr></thead>\n<tbody>\n<tr><td>Color distribution</td><td>Uneven zoning, natural gradation</td><td>Uniform, flat, \"too perfect\"</td></tr>\n<tr><td>Where color sits</td><td>Throughout the crystal, following growth structure</td><td>Dyed: concentrated in cracks/fissures; synthetic: perfectly even</td></tr>\n<tr><td>Saturation</td><td>Subtle variation, lighter and darker zones</td><td>Single flat tone, often over-saturated</td></tr>\n</tbody>\n</table>\n<p><strong>How to do it:</strong></p>\n<ol>\n<li>Look at the stone under daylight (not yellow indoor light, which distorts color).</li>\n<li>Examine whether the color is uniform or shows natural lighter/darker zones — genuine amethyst, citrine, and fluorite almost always show some variation.</li>\n<li>For suspected dye: check cracks and chips — dye pools in surface fissures and looks more intense there.</li>\n</ol>\n<p><strong>Limitations:</strong> Some high-quality natural stones are genuinely uniform in color, and some synthetic stones are deliberately made with simulated zoning. So uniform color is a flag, not a verdict — combine with other tests. Dye tests can fade over time; a cotton swab dampened with acetone (for non-quartz stones) can lift surface dye, but this is mildly destructive.</p>\n<p><strong>Best stones for this test:</strong> Amethyst (most classic case), citrine, fluorite, agate, rose quartz, lapis lazuli. Not useful for naturally uniform stones or opaque dyed stones without cracks to inspect.</p>\n<p><em>Source: GIA Gem Reference Guide — quartz color zoning; mindat.org — amethyst color cause (iron + irradiation).</em></p><h3>⚖️ Test 3: Specific Gravity (Heft) Test</h3>\n<p><strong>The science behind it:</strong> Specific gravity (SG) measures density relative to water. Natural quartz has an SG of 2.65 — meaning a given volume of quartz weighs 2.65 times the same volume of water. Most common glass falls around 2.4-2.6, plastic around 1.0-1.5. Holding two stones of the same size, the denser genuine crystal feels noticeably heavier in the hand (\"good heft\"), while plastic feels suspiciously light.</p>\n<p><strong>Real vs fake at a glance:</strong></p>\n<table>\n<thead><tr><th>Signal</th><th>Genuine</th><th>Fake (glass / plastic)</th></tr></thead>\n<tbody>\n<tr><td>Weight in hand for same size</td><td>Substantial — \"good heft\" (SG 2.65 quartz)</td><td>Lighter (glass ~2.5, plastic ~1.2)</td></tr>\n<tr><td>Ratio to water displacement</td><td>2.65 (quartz), 3.3 (jadeite)</td><td>2.4-2.6 (glass), 1.0-1.5 (plastic)</td></tr>\n<tr><td>Tapping two same-size beads</td><td>Denser, deeper tap</td><td>Hollower tap</td></tr>\n</tbody>\n</table>\n<p><strong>How to do it:</strong></p>\n<ol>\n<li>Compare the suspected stone against a known genuine stone of similar size (or against a glass marble of the same diameter).</li>\n<li>Weigh them in your palm alternately — a genuine quartz bead feels about 10% heavier than an equal-size glass bead.</li>\n<li>For precision: weigh the stone dry, then suspended in water, and divide — but for most home checks, hand heft is enough.</li>\n</ol>\n<p><strong>Limitations:</strong> The difference between quartz (2.65) and glass (2.4-2.6) is small enough that hand heft alone is unreliable without a reference object of the same size. Plastic (1.0-1.5) is obvious, but high-quality glass imitations can feel similar. A precision jewelry scale with water displacement is needed for an accurate SG reading.</p>\n<p><strong>Best stones for this test:</strong> All stones where there is a meaningful density gap — especially distinguishing plastic imitations of any stone, and jadeite (SG 3.3, distinctly heavier than the quartz or serpentine often substituted).</p>\n<p><em>Source: mindat.org — mineral specific gravity data; GIA Gem Reference Guide.</em></p><h3>🔨 Test 2: Hardness / Scratch Test</h3>\n<p><strong>The science behind it:</strong> The Mohs scale ranks minerals by scratch resistance from 1 (talc) to 10 (diamond). Genuine quartz sits at Mohs 7, meaning it can scratch ordinary window glass (about Mohs 5.5) and steel (around Mohs 6). Glass imitations, being softer or equally soft, cannot reliably scratch true glass. The test exploits this hardness gap.</p>\n<p><strong>Real vs fake at a glance:</strong></p>\n<table>\n<thead><tr><th>Signal</th><th>Genuine</th><th>Fake (glass / plastic)</th></tr></thead>\n<tbody>\n<tr><td>Scratching glass</td><td>Quartz (Mohs 7) scratches glass easily</td><td>Glass (Mohs 5.5) cannot scratch glass</td></tr>\n<tr><td>Being scratched by steel</td><td>Steel (Mohs 6) cannot scratch quartz</td><td>Steel can scratch glass imitation</td></tr>\n<tr><td>Edge after scratch</td><td>Leaves a clear groove</td><td>No mark, or only crumbles</td></tr>\n</tbody>\n</table>\n<p><strong>How to do it:</strong></p>\n<ol>\n<li>Take a piece of ordinary window glass (a glass jar you do not mind damaging, never good glassware).</li>\n<li>Press a sharp edge or point of the stone firmly and drag it across the glass.</li>\n<li>A genuine quartz leaves a visible scratch groove; a glass imitation leaves no mark or only a faint streak that rubs off.</li>\n</ol>\n<p><strong>Limitations:</strong> This is a destructive test — it damages both the stone (edge) and the glass. Never use it on finished jewelry, polished pieces, or stones you want to keep pristine. It does not work for genuine soft stones (malachite Mohs 3.5-4, calcite Mohs 3, turquoise Mohs 5-6) which legitimately cannot scratch glass. Use only as a confirmation on quartz-family rough or tumbled stones.</p>\n<p><strong>Best stones for this test:</strong> Quartz family (Mohs 7), topaz (Mohs 8), jadeite (Mohs 6.5-7). Not suitable for soft stones, jewelry, or polished specimens.</p>\n<p><em>Source: mindat.org — Mohs hardness scale; USGS Mineral Database — quartz hardness.</em></p><h3>🟣 Test 6: UV Light (Fluorescence) Test</h3>\n<p><strong>The science behind it:</strong> Some minerals fluoresce — emit visible light — under ultraviolet (UV) radiation, due to trace impurities called activators. Natural fluorite often fluoresces blue or purple; genuine scapolite glows yellow-orange; some natural quartz shows weak fluorescence. The fluorescence pattern of a natural stone differs from glass (usually inert) and from some synthetics (which may fluoresce differently). A 365nm UV flashlight reveals this.</p>\n<p><strong>Real vs fake at a glance:</strong></p>\n<table>\n<thead><tr><th>Signal</th><th>Genuine</th><th>Fake (glass / plastic)</th></tr></thead>\n<tbody>\n<tr><td>Under 365nm UV light</td><td>Specific fluorescence (e.g., fluorite → blue/purple)</td><td>Glass usually inert; some synthetics fluoresce abnormally</td></tr>\n<tr><td>Fluorescence pattern</td><td>Patchy, follows natural growth zones</td><td>Uniform or absent (glass), or too uniform (some synthetics)</td></tr>\n<tr><td>Color of glow</td><td>Species-specific (scapolite yellow, fluorite blue)</td><td>None, or wrong color for the claimed species</td></tr>\n</tbody>\n</table>\n<p><strong>How to do it:</strong></p>\n<ol>\n<li>Use a 365nm UV flashlight (about $10-15 online; the shorter 395nm \"blacklight\" is less precise).</li>\n<li>Darken the room as much as possible.</li>\n<li>Shine the UV on the stone and observe any glow — note the color and whether it is patchy or uniform.</li>\n</ol>\n<p><strong>Limitations:</strong> Not all minerals fluoresce — many genuine stones (including most clear quartz) show no reaction, so a negative result does not mean fake. Fluorescence also varies even within a single mineral species depending on impurities. This test is most useful as confirmation for known fluorescent species (fluorite, scapolite, some calcite, some amber). Requires a UV light source and a dark room.</p>\n<p><strong>Best stones for this test:</strong> Fluorite (reliable blue/purple), scapolite, amber (fluoresces blue-green), some calcite. Not useful as a general test for non-fluorescent species like clear quartz.</p>\n<p><em>Source: mindat.org — mineral fluorescence data; GIA Gem Reference Guide.</em></p><h3>Mineral Data Reference (Mohs Hardness, Specific Gravity, Refractive Index)</h3>\n<p><em>The numbers behind the tests — these are fixed mineralogical facts, not opinion. Use them to verify what the home tests suggest.</em></p>\n<table>\n<thead><tr><th>Stone</th><th>Mohs hardness</th><th>Specific gravity</th><th>Refractive index</th><th>Formula</th><th>Common imitation</th></tr></thead>\n<tbody>\n<tr><td><strong>Amethyst</strong></td><td>7</td><td>2.65</td><td>1.544</td><td>SiO₂ (silicon dioxide)</td><td>Synthetic (lab-grown) purple quartz</td></tr>\n<tr><td><strong>Citrine</strong></td><td>7</td><td>2.65</td><td>1.544</td><td>SiO₂ (silicon dioxide)</td><td>Heat-treated amethyst sold as citrine (very common, often undisclosed)</td></tr>\n<tr><td><strong>Turquoise</strong></td><td>5–6</td><td>2.6–2.9</td><td>~1.62</td><td>CuAl₆(PO₄)₄(OH)₈·4H₂O (hydrated copper aluminum phosphate)</td><td>Howlite dyed blue (the most common fake)</td></tr>\n<tr><td><strong>Lapis Lazuli</strong></td><td>5–5.5</td><td>2.7–2.9</td><td>~1.50</td><td>Lazurite + calcite + pyrite (a rock, not a single mineral)</td><td>Dyed jasper or howlite</td></tr>\n<tr><td><strong>Moldavite</strong></td><td>5–5.5</td><td>2.3–2.4</td><td>~1.49–1.51</td><td>SiO₂-rich natural glass (tektite — formed by meteorite impact)</td><td>Green bottle glass (most common fake)</td></tr>\n<tr><td><strong>Malachite</strong></td><td>3.5–4</td><td>3.6–4.0</td><td>~1.86</td><td>Cu₂CO₃(OH)₂ (copper carbonate hydroxide)</td><td>Plastic / resin</td></tr>\n<tr><td><strong>Jadeite</strong></td><td>6.5–7</td><td>~3.3 (distinctly heavier than substitutes)</td><td>~1.66</td><td>NaAlSi₂O₆ (sodium aluminum silicate — a pyroxene)</td><td>Dyed quartz (most common fake for green jade)</td></tr>\n<tr><td><strong>Obsidian</strong></td><td>5–5.5</td><td>~2.4</td><td>~1.50</td><td>Natural volcanic glass (~70-75% SiO₂, amorphous)</td><td>Industrial glass (the hardest to distinguish — same material family)</td></tr>\n<tr><td><strong>Clear Quartz</strong></td><td>7</td><td>2.65</td><td>1.544</td><td>SiO₂ (silicon dioxide)</td><td>Ordinary glass (most common)</td></tr>\n<tr><td><strong>Rose Quartz</strong></td><td>7</td><td>2.65</td><td>1.544–1.553</td><td>SiO₂ (silicon dioxide)</td><td>Glass dyed pink</td></tr>\n</tbody>\n</table>\n<p><em>Mineral data: GIA Gem Reference Guide, mindat.org, USGS Mineral Database. SG = specific gravity; RI = refractive index.</em></p>\n\n<h2>The 10 Most Faked Crystals</h2>\n<p>These are the ten crystals most often sold as fakes, ranked roughly by how commonly they are imitated. Each entry gives the mineral profile, what gets faked, the key tests that catch the imitations, and the price range that helps you spot a \"too good to be true\" listing. For amethyst and clear quartz — the two most faked — there are dedicated deep-dive guides; the entries here hit the essentials.</p><h3>Amethyst</h3>\n<p><strong>Mineral data:</strong> Formula SiO₂ (silicon dioxide) · Mohs 7 · Specific gravity 2.65 · Refractive index 1.544 · Color cause: Iron + natural irradiation. Primary origins: Brazil, Uruguay, Zambia, Mexico.</p>\n<p><strong>What gets faked:</strong></p>\n<ul>\n<li>Synthetic (lab-grown) purple quartz</li>\n<li>Glass dyed purple</li>\n<li>Heat-treated low-grade amethyst sold as \"citrine\"</li>\n</ul>\n<p><strong>How to tell Amethyst is real — the key tests:</strong></p>\n<ol>\n<li>Color zoning is the headline test — natural amethyst shows subtle lighter/darker purple gradients, especially concentrated at crystal tips. Synthetic amethyst looks uniformly saturated and \"too perfect.\"</li>\n<li>Inclusions under 10x loupe: natural amethyst has needle-like rutile, two-phase gas-liquid inclusions, or \"fingerprints.\" Synthetic amethyst often shows \"breadcrumb\" inclusions from lab seed-crystal growth.</li>\n<li>UV fluorescence: synthetic amethyst frequently shows a blue fluorescence under shortwave UV; natural amethyst is usually inert or shows weak reddish-brown.</li>\n<li>Pricing sanity check: a large \"natural amethyst\" geode at the price of a tumbled stone is almost certainly dyed or reconstituted.</li>\n</ol>\n<p><strong>Price sanity check:</strong> Tumbled stones $2-8; beads $0.50-3 each; small geodes $15-60; large cathedral geodes $100-2000+ depending on size and quality</p>\n<p><em>Source: GIA Gem Reference Guide — quartz; mindat.org — amethyst (Fe³⁺ + irradiation color cause).</em></p>\n<p><a href=\"/gemstone/amethyst-meaning/\">Read the full Amethyst meaning</a> · <a href=\"/product-category/amethyst-crystals/\">Shop Amethyst</a></p><h3>Citrine</h3>\n<p><strong>Mineral data:</strong> Formula SiO₂ (silicon dioxide) · Mohs 7 · Specific gravity 2.65 · Refractive index 1.544 · Color cause: Iron (Fe³⁺) + heat. Primary origins: Brazil, Madagascar, Russia, Spain.</p>\n<p><strong>What gets faked:</strong></p>\n<ul>\n<li>Heat-treated amethyst sold as citrine (very common, often undisclosed)</li>\n<li>Glass dyed yellow/orange</li>\n<li>Synthetic quartz</li>\n</ul>\n<p><strong>How to tell Citrine is real — the key tests:</strong></p>\n<ol>\n<li>Color tells the story: natural citrine is pale yellow to soft amber. The vivid \"burnt orange\" citrine ubiquitous in shops is almost always heat-treated amethyst — disclosure is the issue, not the treatment itself.</li>\n<li>Heat-treated amethyst often retains a subtle reddish-brown undertone and may show faint color zoning remnants from the original purple.</li>\n<li>Reputable sellers disclose heat treatment; the FTC requires it. \"Natural citrine\" priced the same as amethyst is a flag.</li>\n<li>Glass dyed yellow shows dye concentrations in cracks under a loupe.</li>\n</ol>\n<p><strong>Price sanity check:</strong> Tumbled $2-6; beads $0.50-3; small points $5-15; natural untreated citrine commands a premium</p>\n<p><em>Source: GIA Gem Reference Guide — citrine color cause (Fe³⁺ + heat).</em></p>\n<p><a href=\"/gemstone/citrine-meaning/\">Read the full Citrine meaning</a> · <a href=\"/product-category/healing-crystals-jewelry/\">Shop Citrine</a></p><h3>Turquoise</h3>\n<p><strong>Mineral data:</strong> Formula CuAl₆(PO₄)₄(OH)₈·4H₂O (hydrated copper aluminum phosphate) · Mohs 5–6 · Specific gravity 2.6–2.9 · Refractive index ~1.62 · Color cause: Copper (blue), iron (green). Primary origins: Iran, USA (Southwest), China, Mexico, Egypt.</p>\n<p><strong>What gets faked:</strong></p>\n<ul>\n<li>Howlite dyed blue (the most common fake)</li>\n<li>Plastic / resin (block turquoise, \"reconstituted\")</li>\n<li>Magnesite dyed</li>\n<li>Glass</li>\n</ul>\n<p><strong>How to tell Turquoise is real — the key tests:</strong></p>\n<ol>\n<li>Matrix inspection: genuine turquoise has a natural matrix (host rock veins — brown, black, or golden). Dyed howlite has dark veining that looks \"spiderweb\" but the base color is wrong (too uniform blue, matrix too regular).</li>\n<li>The \"too perfect\" test: genuine turquoise varies in color across a piece; dyed howlite and plastic are uniform.</li>\n<li>Specific gravity: plastic block turquoise feels suspiciously light; genuine turquoise has a heftier feel.</li>\n<li>Price flag: large \"natural turquoise\" beads at $1-2 each are almost certainly howlite or plastic.</li>\n<li>Stabilization disclosure: most genuine turquoise on the market is \"stabilized\" (resin-impregnated for durability) — reputable sellers disclose this; it is legitimate, but should not be sold as \"untreated.\"</li>\n</ol>\n<p><strong>Price sanity check:</strong> Genuine tumbled $5-20; beads $1-5; untreated Sleeping Beauty grade $20-100+; fakes often $1-3</p>\n<p><em>Source: GIA Gem Reference Guide — turquoise; mindat.org — turquoise formula and origins.</em></p>\n<p><a href=\"/gemstone/turquoise-meaning/\">Read the full Turquoise meaning</a> · <a href=\"/product-category/healing-crystals-jewelry/\">Shop Turquoise</a></p><h3>Lapis Lazuli</h3>\n<p><strong>Mineral data:</strong> Formula Lazurite + calcite + pyrite (a rock, not a single mineral) · Mohs 5–5.5 · Specific gravity 2.7–2.9 · Refractive index ~1.50 · Color cause: Lazurite sulfur-bearing radicals (blue), pyrite (gold flecks). Primary origins: Afghanistan (primary, finest), Chile, Russia, Pakistan.</p>\n<p><strong>What gets faked:</strong></p>\n<ul>\n<li>Dyed jasper or howlite</li>\n<li>Synthetic lapis (Gilson)</li>\n<li>Sodalite sold as lapis</li>\n<li>Dyed marble</li>\n</ul>\n<p><strong>How to tell Lapis Lazuli is real — the key tests:</strong></p>\n<ol>\n<li>Pyrite flecks: genuine lapis has real gold-colored pyrite flecks scattered irregularly — they look metallic and catch light. Fakes either have no pyrite, or pyrite painted/printed in too-uniform dots.</li>\n<li>Calcite white veining: genuine lapis often shows white calcite streaks. Perfectly uniform deep-blue lapis with no calcite or pyrite is suspicious.</li>\n<li>The \"too blue\" test: dyed howlite and jasper achieve an unnaturally uniform royal blue; genuine lapis has natural variation.</li>\n<li>Sodalite substitution: sodalite is a related blue mineral but lacks pyrite and has a different (often more violet) tone — sold cheaply as \"lapis.\"</li>\n</ol>\n<p><strong>Price sanity check:</strong> Tumbled $3-12; beads $0.50-4; high-grade Afghan with pyrite $10-50 per piece</p>\n<p><em>Source: GIA Gem Reference Guide — lapis lazuli; mindat.org — lazurite.</em></p>\n<p><a href=\"/gemstone/lapis-meaning/\">Read the full Lapis Lazuli meaning</a> · <a href=\"/product-category/healing-crystals-jewelry/\">Shop Lapis Lazuli</a></p><h3>Moldavite</h3>\n<p><strong>Mineral data:</strong> Formula SiO₂-rich natural glass (tektite — formed by meteorite impact) · Mohs 5–5.5 · Specific gravity 2.3–2.4 · Refractive index ~1.49–1.51 · Color cause: Iron and other impurities in natural impact glass. Primary origins: Czech Republic only (Bohemia & Moravia) — the Moldau River valley.</p>\n<p><strong>What gets faked:</strong></p>\n<ul>\n<li>Green bottle glass (most common fake)</li>\n<li>Synthetic green glass with etched texture</li>\n<li>Other green tektites sold as moldavite</li>\n<li>Lab-created imitations</li>\n</ul>\n<p><strong>How to tell Moldavite is real — the key tests:</strong></p>\n<ol>\n<li>Origin is everything: genuine moldavite comes only from the Czech Republic (the Moldau valley). A seller cannot name the source, or offers a huge piece cheaply, is a red flag.</li>\n<li>Lechatelierite bubbles and flow texture: genuine moldavite has distinctive sculpted, wrinkled \"schuss\" texture from its formation, and often contains small bubbles.</li>\n<li>Price flag is extreme: genuine moldavite has become expensive (mined-out supply); large \"moldavite\" at bargain prices is almost certainly bottle glass.</li>\n<li>UV test: some genuine moldavite shows no fluorescence (varies), but green bottle glass often fluoresces differently under UV.</li>\n<li>Color: genuine moldavite is a distinctive forest-green to olive; bottle-glass fakes are often too bright or too uniform.</li>\n</ol>\n<p><strong>Price sanity check:</strong> Genuine small pieces $20-80/gram (prices have risen sharply); medium $100-500; fakes $5-20 for a \"large piece\"</p>\n<p><em>Source: mindat.org — moldavite tektite; GIA Gem Reference Guide — tektites.</em></p>\n<p><a href=\"/gemstone/moldavite-meaning/\">Read the full Moldavite meaning</a> · <a href=\"/product-category/healing-crystals-jewelry/\">Shop Moldavite</a></p><h3>Malachite</h3>\n<p><strong>Mineral data:</strong> Formula Cu₂CO₃(OH)₂ (copper carbonate hydroxide) · Mohs 3.5–4 · Specific gravity 3.6–4.0 · Refractive index ~1.86 · Color cause: Copper. Primary origins: DRC (Congo), Russia, Zambia, Namibia, Australia.</p>\n<p><strong>What gets faked:</strong></p>\n<ul>\n<li>Plastic / resin</li>\n<li>Dyed howlite or magnesite</li>\n<li>Printed vinyl on stone (cheap beads)</li>\n<li>Synthetic</li>\n</ul>\n<p><strong>How to tell Malachite is real — the key tests:</strong></p>\n<ol>\n<li>Banding is the signature: genuine malachite has natural, irregular green banding (light and dark green waves) — never perfectly repeating patterns. Plastic and printed fakes have too-regular bands.</li>\n<li>Specific gravity is a giveaway: genuine malachite is dense (SG 3.6-4.0) — it feels heavy for its size. Plastic feels light.</li>\n<li>Hardness: malachite is genuinely soft (Mohs 3.5-4) — a copper coin or fingernail can scratch it gently. (Conduct gently to avoid damage.)</li>\n<li>Safety note: malachite is copper-bearing — keep it dry and away from acids, and do not make \"malachite water\" for drinking (copper compounds are water-soluble and toxic).</li>\n<li>Color: genuine malachite greens are deep and varied; fakes are often a single flat green with painted bands.</li>\n</ol>\n<p><strong>Price sanity check:</strong> Tumbled $3-10; beads $0.50-4; banded quality $5-30 per piece</p>\n<p><em>Source: GIA / USGS — copper-bearing mineralogy; mindat.org — malachite.</em></p>\n<p><a href=\"/gemstone/malachite-meaning/\">Read the full Malachite meaning</a> · <a href=\"/product-category/healing-crystals-jewelry/\">Shop Malachite</a></p><h3>Jadeite</h3>\n<p><strong>Mineral data:</strong> Formula NaAlSi₂O₆ (sodium aluminum silicate — a pyroxene) · Mohs 6.5–7 · Specific gravity ~3.3 (distinctly heavier than substitutes) · Refractive index ~1.66 · Color cause: Chromium (emerald green \"imperial jade\"), iron (other greens, lavender). Primary origins: Myanmar (primary source for gem jadeite), Guatemala, Russia, Japan.</p>\n<p><strong>What gets faked:</strong></p>\n<ul>\n<li>Dyed quartz (most common fake for green jade)</li>\n<li>Serpentine (a softer, cheaper green stone)</li>\n<li>Nephrite (a different, legitimate jade mineral — disclosure issue)</li>\n<li>Glass and plastic</li>\n<li>Dyed 'jade' of unknown stone</li>\n</ul>\n<p><strong>How to tell Jadeite is real — the key tests:</strong></p>\n<ol>\n<li>Specific gravity is the strongest home test: genuine jadeite (SG 3.3) feels distinctly heavy — heavier than quartz (2.65) of the same size. Most substitutes (serpentine, dyed quartz) feel lighter.</li>\n<li>The \"coin tap\" sound: genuine jadeite produces a clear, resonant chime when tapped with a coin (its dense structure); serpentine and glass sound dull.</li>\n<li>Cold to touch: jadeite has high thermal conductivity and feels cool.</li>\n<li>Color: dyed green \"jade\" often shows dye concentrations in cracks and looks unnaturally uniform. Genuine jadeite color comes from chromium and varies naturally.</li>\n<li>For high-value jadeite (bangles, carvings claiming imperial grade), a gemological lab certificate is essential — home tests cannot distinguish treated dyed jadeite from natural.</li>\n</ol>\n<p><strong>Price sanity check:</strong> Vast range: ordinary carved \"jade\" $5-30; genuine jadeite bangles $50-500; imperial jadeite $1000-100,000+; fakes often under $20</p>\n<p><em>Source: GIA Gem Reference Guide — jadeite vs. nephrite; mindat.org — jadeite.</em></p>\n<p><a href=\"/gemstone/jadeite-meaning/\">Read the full Jadeite meaning</a> · <a href=\"/product-category/healing-crystals-jewelry/\">Shop Jadeite</a></p><h3>Obsidian</h3>\n<p><strong>Mineral data:</strong> Formula Natural volcanic glass (~70-75% SiO₂, amorphous) · Mohs 5–5.5 · Specific gravity ~2.4 · Refractive index ~1.50 · Color cause: Tiny mineral inclusions (black), cristobalite (snowflake patterns), thin-film interference (rainbow). Primary origins: Mexico, USA, Iceland, Italy, Ethiopia, Japan.</p>\n<p><strong>What gets faked:</strong></p>\n<ul>\n<li>Industrial glass (the hardest to distinguish — same material family)</li>\n<li>Molded black glass beads</li>\n<li>Fake 'snowflake' obsidian (painted white spots on black glass)</li>\n</ul>\n<p><strong>How to tell Obsidian is real — the key tests:</strong></p>\n<ol>\n<li>Obsidian is itself a natural glass — so distinguishing it from manufactured glass is genuinely difficult. This is the honest caveat.</li>\n<li>Inclusions are the key: genuine obsidian often has natural mineral inclusions, microcrystals (cristobalite in snowflake obsidian), or chatoyant bands. Industrial glass tends to be too uniform or have manufacturing bubbles.</li>\n<li>Snowflake obsidian: the \"snowflakes\" are natural cristobalite crystals — irregular, fern-like. Painted-on white spots on fake snowflake obsidian look too regular and sit on the surface.</li>\n<li>Rainbow obsidian: genuine rainbow obsidian shows concentric color bands (from thin-film interference) visible when lit from the right angle — difficult to fake.</li>\n<li>Price: obsidian is genuinely affordable, so fakes are less common than for amethyst or turquoise — but \"too perfect\" mirror-polished uniform black glass can still be manufactured.</li>\n</ol>\n<p><strong>Price sanity check:</strong> Tumbled $2-6; beads $0.30-2; mirror-polished spheres $8-30; fakes similar prices but uniform perfection</p>\n<p><em>Source: USGS — volcanic glass; mindat.org — obsidian.</em></p>\n<p><a href=\"/gemstone/obsidian-meaning/\">Read the full Obsidian meaning</a> · <a href=\"/product-category/healing-crystals-jewelry/\">Shop Obsidian</a></p><h3>Clear Quartz</h3>\n<p><strong>Mineral data:</strong> Formula SiO₂ (silicon dioxide) · Mohs 7 · Specific gravity 2.65 · Refractive index 1.544 · Color cause: Colorless (no impurities). Primary origins: Brazil, Madagascar, Arkansas (USA), Himalayas.</p>\n<p><strong>What gets faked:</strong></p>\n<ul>\n<li>Ordinary glass (most common)</li>\n<li>Reconstituted quartz (quartz powder melted with glass)</li>\n<li>Synthetic lab-grown quartz</li>\n<li>Lead crystal glass (\"crystal\" naming trap)</li>\n</ul>\n<p><strong>How to tell Clear Quartz is real — the key tests:</strong></p>\n<ol>\n<li>Bubbles under 10x loupe are the #1 signal — glass has round air bubbles; genuine clear quartz has irregular inclusions (needles, veils, mineral flecks) or is inclusion-free.</li>\n<li>Hardness test: genuine clear quartz (Mohs 7) scratches glass; glass imitations cannot.</li>\n<li>The \"crystal quartz\" naming trap — the glass industry calls leaded glass \"crystal\" (lead crystal, crystal glass). \"Crystal quartz\" sold cheaply is often glass. Natural quartz is properly called \"quartz.\"</li>\n<li>Three quality tiers to distinguish: natural clear quartz (has minor inclusions), clarified/reconstituted (too perfect, may show faint flow lines), and pure glass (bubbles, no quartz characteristics).</li>\n<li>Double refraction: genuine quartz shows slight doubling when you look through it at a sharp angle (text appears doubled); glass does not — but this needs magnification to see.</li>\n</ol>\n<p><strong>Price sanity check:</strong> Small tumbled $1-4; small points $3-10; clusters $10-50; large cathedral points $30-300; museum-grade clusters $200-2000+</p>\n<p><em>Source: mindat.org — quartz; GIA Gem Reference Guide — quartz RI 1.544, birefringence 0.009.</em></p>\n<p><a href=\"/gemstone/quartz-meaning/\">Read the full Clear Quartz meaning</a> · <a href=\"/product-category/clear-quartz-crystals/\">Shop Clear Quartz</a></p><h3>Rose Quartz</h3>\n<p><strong>Mineral data:</strong> Formula SiO₂ (silicon dioxide) · Mohs 7 · Specific gravity 2.65 · Refractive index 1.544–1.553 · Color cause: Titanium, manganese + irradiation. Primary origins: Brazil, Madagascar, South Africa, India, USA.</p>\n<p><strong>What gets faked:</strong></p>\n<ul>\n<li>Glass dyed pink</li>\n<li>Plastic beads (cheap bracelets)</li>\n<li>Synthetic quartz</li>\n<li>Reconstituted (pink quartz powder + glass)</li>\n</ul>\n<p><strong>How to tell Rose Quartz is real — the key tests:</strong></p>\n<ol>\n<li>Color variation: genuine rose quartz shows subtle pink variation and often a slightly cloudy appearance. Glass and plastic look uniform and clear.</li>\n<li>Hardness test: genuine rose quartz (Mohs 7) scratches glass; plastic and glass do not.</li>\n<li>Temperature: genuine rose quartz feels cool and stays cool; plastic warms immediately.</li>\n<li>The \"too cheap bracelet\" test: a 10mm bead rose quartz bracelet for $2-3 on a marketplace is very likely plastic or glass — genuine rose quartz beads cost more to cut and string.</li>\n<li>Asterism (star effect): some genuine rose quartz shows a six-rayed star when cut en cabochon and lit — a strong authenticity signal.</li>\n</ol>\n<p><strong>Price sanity check:</strong> Tumbled $2-6; beads $0.30-2; raw chunks $5-15; fakes similar prices</p>\n<p><em>Source: mindat.org — rose quartz (Ti/Mn + irradiation color cause).</em></p>\n<p><a href=\"/gemstone/rose-quartz-meaning/\">Read the full Rose Quartz meaning</a> · <a href=\"/product-category/healing-crystals-jewelry/\">Shop Rose Quartz</a></p><p><em>For the full 10-test overview across all crystal types, start with <a href=\"/blog/how-to-tell-if-crystal-is-real/\">How to Tell If a Crystal Is Real (full 10-test guide)</a>.</em></p>\n\n<h2>When to Use Professional Tools</h2>\n<p>The tools below cover the tests in this guide. Most are inexpensive; the lab certificate is reserved for high-value specimens.</p>\n<ul>\n<li>A 10x jeweler's loupe is the most valuable tool across all ten stones. It reveals bubbles in glass (amethyst, citrine, clear quartz, rose quartz), dye concentrations in cracks (turquoise, lapis, malachite), the texture of pyrite in lapis, and the natural inclusions that separate genuine stones from manufactured perfection.</li>\n<li>A Mohs hardness reference confirms the quartz family (amethyst, citrine, clear quartz, rose quartz all at Mohs 7) by their ability to scratch glass. Use only on rough stones — never on jewelry or polished pieces.</li>\n<li>A 365nm UV flashlight helps with a few stones on this list: synthetic amethyst (blue fluorescence), fluorite species, and some amber. For most of the ten, it is a secondary tool rather than a primary one.</li>\n<li>A gemological refractometer measures refractive index precisely, distinguishing quartz (1.544) from glass (1.50) and jadeite (1.66) from its substitutes. A professional tool — most buyers will rely on a gemologist rather than own one.</li>\n<li>For high-value stones on this list — jadeite bangles, moldavite over a few hundred dollars, untreated Sleeping Beauty turquoise, large fine amethyst geodes — a gemological laboratory certificate is the only definitive answer. Home tests narrow the odds; a lab report settles them.</li>\n</ul>\n<p><em>For high-value specimens (jadeite, imperial-grade amethyst, moldavite, large geodes), a gemological laboratory certificate is the only definitive answer — home tests narrow the odds, they do not replace a professional report.</em></p>\n\n<h2>Frequently Asked Questions About Real vs Fake Crystals</h2>\n<h3>Which crystals are most commonly faked?</h3>\n<p>The most commonly faked crystals are, in rough order: amethyst (synthetic and dyed glass), citrine (heat-treated amethyst sold as natural), turquoise (dyed howlite and plastic), lapis lazuli (dyed jasper and sodalite), moldavite (green bottle glass), malachite (plastic and printed vinyl), jadeite (dyed quartz and serpentine), obsidian (industrial glass, though harder to detect), clear quartz (glass and reconstituted), and rose quartz (glass and plastic). These ten cover the great majority of fakes a buyer will encounter, because each is popular, visually copyable, and — for the high grades — valuable enough to make substitution profitable.</p>\n<h3>How can you tell if a crystal is fake?</h3>\n<p>Apply the general tests (bubbles, temperature, hardness, price, naming) plus the one species-specific test for the stone. For turquoise, look for natural matrix and color variation. For lapis, look for real pyrite flecks. For jadeite, feel the density (it should be distinctly heavy). For moldavite, confirm Czech origin. For any transparent stone (amethyst, citrine, clear quartz, rose quartz), check for round bubbles under a 10x loupe — bubbles mean glass. Run the tests together; a genuine stone passes several, a fake fails several.</p>\n<h3>What is the most faked crystal?</h3>\n<p>Turquoise and amethyst lead the list. Turquoise is faked constantly because genuine untreated turquoise is expensive and dyed howlite copies its color closely — the \"turquoise\" in much inexpensive jewelry is dyed howlite or plastic. Amethyst is faked constantly because it is the most popular crystal and synthetic amethyst (chemically identical) plus dyed glass fill the market. Moldavite deserves a special mention: because genuine moldavite is rare and has become expensive, the fake rate is extremely high — large \"moldavite\" pieces at low prices are almost always green bottle glass.</p>\n<h3>Is fake turquoise common?</h3>\n<p>Yes, extremely common. Genuine untreated turquoise is relatively expensive (especially fine grades like Sleeping Beauty), and dyed howlite — a cheap white mineral that takes blue dye well — copies turquoise's color closely enough to fool casual buyers. The result is that a large share of \"turquoise\" in inexpensive jewelry and beads is actually dyed howlite, plastic \"block turquoise\" (resin with turquoise dust), or magnesite. The tests: look for natural matrix (host-rock veining, never too uniform), color variation (genuine turquoise varies; dyed howlite is uniform), and the right density (plastic feels light). A reputable seller discloses stabilization, which is legitimate, and names the origin.</p>\n<h3>Where can I buy genuine crystals that are not fake?</h3>\n<p>Look for sellers who do three things across all these heavily faked stones: name each stone by its actual mineral species (not vague terms), disclose treatments (dyed, heat-treated, stabilized, lab-created), and state a specific origin. Beyond that, check for mineral data availability, a clear return policy, and real photographs showing natural variation between pieces. The crystal collection on this site names stones and sources precisely because these are the stones where fakes concentrate — naming and sourcing are how you verify rather than trust.</p>\n<h3>How much do real crystals cost vs fakes?</h3>\n<p>Fakes are dramatically cheaper than genuine stones, especially for high-value species. A few ratios: genuine moldavite starts around $20-80 per gram, while green-glass fakes sell for $5-20 for a large piece. Genuine untreated turquoise beads run $1-5 each, while dyed howlite beads cost cents. Genuine jadeite bangles start around $50 and fine imperial jadeite reaches thousands, while dyed-quartz \"jade\" bangles sell under $20. The absolute price matters less than the ratio to the species' market range — a price far below the established range for that stone and grade is the strongest pre-purchase warning.</p>\n<h3>Are lab-created crystals considered fake?</h3>\n<p>Lab-created stones are genuine in composition (synthetic amethyst is real SiO₂), but they are not natural — they were grown in a factory rather than mined. Whether they count as \"fake\" depends on disclosure. Sold as \"lab-created\" or \"synthetic,\" they are legitimate and often beautiful. Sold as natural without disclosure, they are misleading and against FTC guidelines. For the stones on this list — especially amethyst, citrine, and clear quartz — always check the listing for \"lab-created,\" \"synthetic,\" or \"heat-treated,\" and ask the seller directly if you want a natural specimen.</p>\n<h3>Are fake crystals dangerous?</h3>\n<p>Most fake crystals are not health-hazardous — they are glass, plastic, or dyed stone, which are inert. The real cost is financial and emotional: paying for something you did not receive. A few mineral-specific notes apply across this list: malachite is copper-bearing, so \"malachite water\" (soaking and drinking) is not safe. Dyed stones (turquoise, lapis, agate) can bleed pigment onto skin or fabric. Beyond these specific cases, the concern with fakes is honesty, not toxicity.</p>\n<h3>Can home tests spot all fakes?</h3>\n<p>Home tests do not catch every fake — they catch the obvious ones. Glass sold as quartz, plastic sold as turquoise, and dyed howlite sold as lapis are easily filtered with a $10 loupe and the species-specific tests. But sophisticated imitations — well-made synthetic quartz, expertly reconstituted material, high-quality dyed stones — can pass several home tests. For valuable specimens (jadeite, moldavite, untreated turquoise, fine amethyst geodes), a gemological laboratory report is the only definitive answer. Think of home tests as a strong first filter that handles the bulk of the market, not a final verdict on expensive pieces.</p>\n<h3>Why is moldavite so often faked?</h3>\n<p>Moldavite is faked so often because genuine supply is scarce and shrinking, while demand has risen sharply. Moldavite is a tektite — natural glass formed by a meteorite impact about 15 million years ago — and it is found only in the Czech Republic, in the Moldau River valley. The deposits are largely mined out, which has driven prices up steeply. That combination of high price, limited supply, and a material (green glass) that visually approximates moldavite creates a strong incentive to substitute. The result is that large \"moldavite\" pieces at bargain prices are almost always green bottle glass. The tests: confirm Czech origin, look for natural lechatelierite bubbles and sculpted texture, and treat price as a primary signal.</p>\n<h3>Is dyed howlite always sold as turquoise?</h3>\n<p>Very often. Howlite is a soft, white, porous mineral that takes blue dye exceptionally well, which makes it the most common substitute for turquoise. It is also sometimes dyed to imitate lapis or red coral. There is nothing wrong with howlite itself — it is a legitimate stone — but when dyed blue and sold as turquoise without disclosure, it is misleading. The tests: dyed howlite usually has a uniform royal-blue color (genuine turquoise varies), dark veining that looks too regular, and no genuine matrix. A reputable seller labels dyed howlite honestly rather than passing it off as turquoise.</p>\n<p class=\"gentle-note\"><em>This guide covers the stones most often sold as imitations. Home tests help you spot common fakes, but for valuable specimens (jadeite, moldavite, untreated turquoise), a gemological lab report is the gold standard. Crystal meanings and energetic properties are separate from authenticity.</em></p>\n\n<h2>How to Buy Genuine Crystals (Without Getting Fooled)</h2>\n<p>Across all ten of these heavily faked stones, the same seller signals separate reputable sources from those moving imitations. If you are shopping for any stone on this list, these five checks come first.</p>\n<h3>Five Signs of a Reputable Seller</h3>\n<ul>\n<li>Naming transparency. The listing names the actual mineral species — \"Natural Turquoise,\" \"Lapis Lazuli,\" \"Jadeite\" — not vague terms. Treatments are disclosed: dyed howlite sold as turquoise, heat-treated amethyst sold as citrine, stabilized turquoise, dyed quartz sold as jade. A seller who names stones correctly is signaling they know the difference.</li>\n<li>Locality disclosure. The listing states a specific origin — Afghanistan for lapis, the Czech Republic for moldavite, Iran or the American Southwest for turquoise, Myanmar for jadeite. Origin matters for these stones because it affects value and because some origins (Czech-only moldavite) are part of how you confirm authenticity.</li>\n<li>Mineral data availability. The seller provides Mohs hardness, specific gravity, or refractive index — or links to it. Sellers who understand mineralogy bother; sellers moving fakes usually do not. The data also lets you cross-check the home tests.</li>\n<li>Clear return policy. A 30-day return policy shifts risk to the seller and gives you time to test the stone at home. Sellers who move fakes resist returns because returned fakes expose them.</li>\n<li>Real photographs of the actual piece. Natural stones vary — each turquoise bead has its own matrix, each lapis chunk its own pyrite pattern. Mass-produced fakes look identical across listings. Real photos showing natural variation are a positive sign; uniform catalog shots are not.</li>\n</ul>\n<h3>How Earthward Approaches This</h3>\n<p>At Earthward, we name each stone by its mineral species, state the origin where we know it, and disclose treatments honestly. The stones on this list — amethyst, clear quartz, turquoise, lapis, and the rest — are exactly where fakes concentrate, so we are deliberate about naming and sourcing. \"Return to what's real\" means we tell you what you are holding, with its natural variation and inclusions, rather than hiding behind a vague label.</p>\n<p><a href=\"/product-category/healing-crystals-jewelry/\"><strong>Browse genuine crystal jewelry</strong></a></p>\n<p><em>We name our stones and sources — return to what's real.</em></p>",
  "images": {
    "hero": {
      "file": "assets/images/generated/11.authenticity/most-faked-crystals/most-faked-crystals-hero.webp",
      "source_type": "comparison",
      "alt": "A collection of the ten most faked crystals arranged together, including amethyst, turquoise, lapis, malachite, and clear quartz, photographed in soft natural light, realistic mineral photography, no text"
    },
    "comparison": {
      "file": "assets/images/generated/11.authenticity/most-faked-crystals/most-faked-crystals-turquoise.webp",
      "source_type": "comparison",
      "alt": "A genuine turquoise stone with natural brown matrix compared side by side with dyed howlite of uniform blue color, realistic mineral photography, no text"
    },
    "test": {
      "file": "assets/images/generated/11.authenticity/most-faked-crystals/most-faked-crystals-lapis.webp",
      "source_type": "diagram",
      "alt": "A genuine lapis lazuli stone with visible gold pyrite flecks compared side by side with a fake of uniform blue without pyrite, realistic mineral photography, no text"
    }
  }
}