{
  "title": "151 Angel Number Meaning: Love, Money & Crystals",
  "slug": "151-angel-number-meaning",
  "url": "/151-angel-number-meaning/",
  "number": "151",
  "is_hub": false,
  "theme": "Mirrored Independence / Reflected Freedom",
  "unique_angle": "mirrored independence - self-leadership reflected into freedom",
  "primary_intent": "mirrored independence",
  "secondary_intent": "reflected freedom",
  "emotional_state": "claiming mirrored independence and freedom",
  "recommended_action": "claim your independence - 1's self reflected through 5's freedom",
  "avoid_claims": [
    "guarantees manifestation",
    "means you will become rich",
    "will attract your soulmate",
    "is a message from angels as absolute fact",
    "cures or treats any medical condition"
  ],
  "numerology": {
    "single_digit": 1,
    "reduced_sum": "1+5+1=7",
    "reduced_meaning": "reduces to 7 - mirrored independence opening into wisdom",
    "is_master_number": false,
    "master_note": ""
  },
  "crystals": {
    "best_overall": {
      "slug": "carnelian",
      "name": "Carnelian",
      "overview": {
        "Chakra": "Sacral, Solar Plexus, Root",
        "Zodiac": "Aries, Taurus, Virgo",
        "Element": "Fire",
        "Number": "5, 6",
        "Color": "Orange, red-orange, reddish-brown",
        "Intentions": "Courage, Motivation, Creativity",
        "Best for": "Confidence, Starting projects, Creative work",
        "Forms": "Bracelet, Ring, Pendant, Tumbled, Cabochon, Bead"
      },
      "meaning": "/gemstone/carnelian-meaning/",
      "shop": "/product-category/carnelian-crystals/",
      "reason": "best for mirrored independence"
    },
    "best_love": {
      "slug": "citrine",
      "name": "Citrine",
      "overview": {
        "Chakra": "Solar Plexus, Sacral",
        "Zodiac": "Aries, Leo",
        "Element": "Fire",
        "Number": "2, 3",
        "Color": "Yellow, golden-orange, brownish-yellow",
        "Intentions": "Abundance, Confidence, Motivation",
        "Best for": "Wealth, Confidence, Morning energy",
        "Forms": "Bracelet, Ring, Pendant, Tumbled, Raw point, Cluster, Geode"
      },
      "meaning": "/gemstone/citrine-meaning/",
      "shop": "/product-category/citrine-crystals/",
      "reason": "best for confident mirrored freedom"
    },
    "best_protection": {
      "slug": "tiger-eye",
      "name": "Tiger Eye",
      "overview": {
        "Chakra": "Solar Plexus, Root, Sacral",
        "Zodiac": "Leo, Capricorn",
        "Element": "Fire",
        "Color": "Golden brown (also blue/red)",
        "Intentions": "Courage, Confidence, Protection",
        "Best for": "Confidence, Willpower, Grounding",
        "Forms": "Cabochon, Bead, Tumbled, Sphere"
      },
      "meaning": "/gemstone/tiger-eye-meaning/",
      "shop": "/product-category/tiger-eye-crystals/",
      "reason": "best for grounded self-leadership"
    },
    "best_manifestation": {
      "slug": "sunstone",
      "name": "Sunstone",
      "overview": {
        "Chakra": "Sacral, Solar Plexus",
        "Zodiac": "Leo, Libra",
        "Element": "Fire",
        "Number": "—",
        "Color": "Orange, Red, Yellow",
        "Intentions": "Confidence, Joy, Warmth",
        "Best for": "Confidence, Mood, Motivation",
        "Forms": "Bead bracelet, Cabochon pendant, Tumbled stone, Sphere, Free-form"
      },
      "meaning": "/gemstone/sunstone-meaning/",
      "shop": "/product-category/sunstone-crystals/",
      "reason": "best for radiant independence"
    },
    "best_daily_wear": {
      "slug": "amazonite",
      "name": "Amazonite",
      "overview": {
        "Chakra": "Heart, Throat",
        "Zodiac": "Virgo, Aquarius",
        "Element": "Water",
        "Color": "Blue-green, turquoise-green",
        "Intentions": "Courage, Truth, Communication",
        "Best for": "Communication, Calm, Honesty",
        "Forms": "Pendant, Tumbled, Bracelet, Palm stone"
      },
      "meaning": "/gemstone/amazonite-meaning/",
      "shop": "/product-category/amazonite-crystals/",
      "reason": "best for brave daily freedom"
    }
  },
  "needs_misconception_section": false,
  "module_weights": {
    "M4_love": "normal",
    "M5_money": "normal"
  },
  "related_numbers": [
    "515",
    "115",
    "1551"
  ],
  "related_reason": "515 is its mirror; 115 amplifies it; 1551 quadruples it",
  "rank_math_title": "151 Angel Number Meaning: Love, Money & Crystals",
  "rank_math_description": "<p>151 angel number meaning: mirrored independence, with two 1s reflecting self-leadership into freedom. Explore its spiritual message, numerology, love, money, and the best crystals to pair with it.</p>",
  "rank_math_focus_keyword": "151 angel number",
  "excerpt": "<p>The 151 angel number mirrors independence — two 1s reflecting self-leadership into the freedom of a central 5. A gentle invitation to claim your own direction, in love, money, and daily life.</p>",
  "diffHints": {
    "unique_angle": "mirrored independence - self-leadership reflected into freedom",
    "emotional_state": "claiming mirrored independence and freedom",
    "recommended_action": "claim your independence - 1's self reflected through 5's freedom",
    "avoid_claims": [
      "guarantees manifestation",
      "means you will become rich",
      "will attract your soulmate",
      "is a message from angels as absolute fact",
      "cures or treats any medical condition"
    ],
    "module_weights": {
      "M4_love": "normal",
      "M5_money": "normal"
    }
  },
  "content": "<p>You glance at the clock and it reads 1:51. A receipt totals $1.51. A license plate ahead ends in 151. When the same number keeps following you, many spiritual traditions interpret it as a gentle nudge to pay attention. The <strong>151 angel number</strong> carries a distinctive signature: it is a mirror. Two ones stand on either side of a five, reflecting self-leadership outward into freedom. At its heart, 151 speaks to <em>mirrored independence</em> — the moment your inner authority becomes visible in how you live. Spiritually, it invites you to trust your own direction. Psychologically, it points to a shift from seeking permission to giving yourself permission. As a mindfulness cue, it simply asks: are my choices today truly mine? You may read it as encouragement to step forward on your own terms, with the freedom to choose your path.</p>\n\n<h2>What Does 151 Mean? (Quick Answer)</h2>\n<p><p>The 151 angel number blends the independence of two 1s with the freedom of a central 5, suggesting a turning point where self-leadership becomes lived freedom. Many traditions read it as a prompt to claim your direction, make a bold but considered choice, and trust your own judgment. Numerologically it reduces to 7 (1+5+1), adding a layer of inner wisdom to its core message of independence. It is neither a luck charm nor a fixed prediction — it is an invitation to reflect, then act.</p></p>\n<ul>\n<li><strong>Core meaning:</strong> Mirrored Independence / Reflected Freedom</li>\n<li><strong>Key message:</strong> mirrored independence - self-leadership reflected into freedom</li>\n<li><strong>Action:</strong> claim your independence - 1's self reflected through 5's freedom</li>\n</ul>\n\n<h2>The Spiritual Meaning of 151</h2>\n<p><p>What makes 151 feel different from other numbers you might see is its mirror shape. The digit 1 appears on both ends, holding the same number the way two hands hold something precious — and in the middle sits 5, the number of movement, change, and freedom. Many spiritual teachers read this structure as a picture of independence reflected into the world: who you are in private begins to shape what you do in public.</p>\n<p>Spiritually, 1 represents the self that leads — the part of you that decides, that takes responsibility, that says \"this is mine to carry.\" When that energy appears on both sides of a number, it suggests a wholeness, a self that is consistent rather than split. The 5 between them is the bridge — the lived expression of that inner certainty moving through real choices, real conversations, real risks. Independence stops being a stance you defend and becomes a freedom you inhabit.</p>\n<p>If 151 keeps appearing, it may be reflecting a question you have been circling: where have you outsourced your authority? Where are you waiting for permission that, in truth, only you can give? The number does not demand a dramatic exit or a reinvention. More often it points to small, steady corrections — speaking a preference you have swallowed, finishing something you began on borrowed conviction, choosing a path because it is yours rather than because it is expected. Mirrored independence is not isolation; it is the freedom to relate, work, and love from a centered place rather than a reactive one. You may use this number as a reminder that your inner compass has always been the one you were following.</p></p>\n\n<h2>The Numerology Behind 151</h2>\n<p><p>Numbers carry symbolic weight in many numerology traditions, and 151 has a structure worth slowing down to read. Its meaning unfolds across two layers — the energies of its individual digits, and the single number it reduces to when you add them together.</p></p>\n<ul>\n<li><strong>Single digit:</strong> 1 (mirrored independence)</li>\n<li><strong>Reduced sum:</strong> 1+5+1=7 → reduces to 7 - mirrored independence opening into wisdom</li>\n</ul>\n<p><p>The digit 1 governs new beginnings, initiative, and self-directed action. In 151 it appears twice, and repetition in numerology is read as amplification — not a louder version of the same message, but a deeper one. Two 1s suggest an independence that has steadied itself, a self-leadership that no longer needs to prove itself because it has already been tested. Between them sits 5, the number of change, freedom, and lived experience. So the shape of 151 tells a small story: a self (1) that has earned its freedom (5) and returned to itself (1) changed.</p>\n<p>When you add the digits — 1 + 5 + 1 — you get 7. Numerologically 7 is the number of introspection, wisdom, and inner knowing. This is the hidden layer beneath 151's outward confidence. It suggests that the independence this number points to is not recklessness or stubborn individualism; it is independence grounded in reflection. The freedom of 5, filtered through the wisdom of 7, becomes a freedom that knows itself. If 151 has been showing up for you, this reduction offers a quiet qualifier: act on your own judgment, yes — but first take the moment of silence that lets good judgment arrive.</p></p>\n\n<h2>151 in Love &amp; Twin Flame</h2>\n<p><p>In matters of love, 151 turns the lens inward before it turns outward. Because the number is built around independence, it often appears when your relationships are being reshaped by how you relate to yourself. Many traditions read it as a sign that healthy partnership begins with a self that knows its own center — not a self that is closed off, but one that no longer disappears into another person to feel whole.</p>\n<p>If you are single, 151 may be inviting you to ask what kind of love you actually want, rather than the kind you have been accepting by default. The mirror of two 1s suggests consistency — that who you are when no one is watching should match who you bring into a relationship. This is often a season of reclaiming preferences, standards, and the freedom to say both yes and no without apology.</p>\n<p>If you are in a relationship, 151 can highlight where independence and closeness need rebalancing. It does not push you toward separation; more often it points to a partnership where two whole people choose each other rather than two halves completing each other. Speaking your own mind, keeping the friendships and interests that are yours alone, taking responsibility for your own growth — these are not threats to love, they are what make love sustainable. In twin flame language, 151 is sometimes read as a reminder that the most magnetic version of you is the self-led one — that chasing a connection outside yourself before you have anchored it within tends to reproduce the same old patterns in new faces. The number is not a promise of reunion or arrival; it is an invitation to become the person whose choices are already free, and to let love meet you there.</p></p>\n\n<h2>151 in Money &amp; Career</h2>\n<p><p>When it comes to money and career, 151 reframes abundance as something that flows from self-direction. The 1 energy governs initiative and leadership; the 5 governs adaptability and movement. Together they suggest that financial growth at this moment is tied less to a fixed plan and more to your willingness to take ownership of your direction and adjust as you go.</p>\n<p>In a career, 151 may surface when you are standing at a choice point — taking the lead on a project, stepping into work that is more authentically yours, or finally pursuing the idea you have been sitting on. The number does not promise a particular outcome or guarantee prosperity. Rather, it points to a posture: are you building something that reflects your own judgment, or are you waiting for someone else to authorize your next move? Many people find that the freedom the 5 represents shows up practically as the willingness to negotiate, to raise your rate, to start the side project, to walk away from terms that quietly diminish you.</p>\n<p>Financially, the reduction to 7 adds a note of discernment. Not every opportunity that looks like freedom is one. Some independence is real and earned; some is just a new kind of trap dressed in different language. 151 invites you to combine boldness with reflection — to act on your own authority, and to do the quiet thinking that tells you which actions are actually yours to take. You may use this number as a mindfulness reminder to make one self-directed money choice this week, however small, and notice how it feels to move from your own center rather than from habit or fear.</p></p>\n\n<h2>Best Crystals for Angel Number 151</h2>\n<p><p>Because 151 is a number of self-led freedom, the stones that resonate with it tend to share certain qualities — warmth, courage, clear self-expression, and a steady sense of personal power. You can carry one of these crystals as a tangible anchor for the message, a small daily reminder to act from your own center rather than from outside pressure.</p></p>\n<h3>Best Overall Crystal for 151</h3>\n<p><p>Carnelian resonates with 151's call for mirrored independence. Long associated with courage and motivation, this warm orange stone carries the fire element that matches the boldness of two 1s. Many people reach for it when they need the nerve to make a self-directed choice, or to keep moving once they have made one. As a companion for 151, it can serve as a daily reminder that your independence is something you live, not something you only think about.</p></p>\n<p><em>Carnelian</em> — best for mirrored independence. <a href=\"/gemstone/carnelian-meaning/\">Read full Carnelian meaning</a> · <a href=\"/product-category/carnelian-crystals/\">Shop Carnelian</a></p>\n<h3>Best Crystal for Love</h3>\n<p><p>When 151 appears, Citrine offers a confident, sunlit kind of support. Known for its association with personal power and a generous, abundant mood, this golden stone pairs naturally with the freedom the central 5 represents. If you are reclaiming your own direction in love or money, Citrine is the stone many turn to as a small daily prompt to choose from confidence rather than from scarcity or fear.</p></p>\n<p><em>Citrine</em> — best for confident mirrored freedom. <a href=\"/gemstone/citrine-meaning/\">Read full Citrine meaning</a> · <a href=\"/product-category/citrine-crystals/\">Shop Citrine</a></p>\n<h3>Best Crystal for Protection &amp; Grounding</h3>\n<p><p>If you keep seeing 151, try working with Tiger Eye. A stone of grounding and willpower, it supports the kind of self-leadership that stays steady rather than impulsive. The independence 151 points to is not recklessness — it is earned, considered, and rooted — and Tiger Eye is traditionally carried to bring exactly that grounded quality to bold decisions. Hold it when a choice feels bigger than you are used to making on your own.</p></p>\n<p><em>Tiger Eye</em> — best for grounded self-leadership. <a href=\"/gemstone/tiger-eye-meaning/\">Read full Tiger Eye meaning</a> · <a href=\"/product-category/tiger-eye-crystals/\">Shop Tiger Eye</a></p>\n<h3>Best Crystal for Manifestation</h3>\n<p><p>Sunstone pairs naturally with 151's radiant energy. As a stone of warmth, joy, and self-worth, it reflects the outward-facing side of independence — the version that is willing to be seen, to take up space, to lead. Where some stones steady you, Sunstone tends to brighten you, making it a fitting companion for the part of 151's message that asks you to let your independence become visible rather than hidden.</p></p>\n<p><em>Sunstone</em> — best for radiant independence. <a href=\"/gemstone/sunstone-meaning/\">Read full Sunstone meaning</a> · <a href=\"/product-category/sunstone-crystals/\">Shop Sunstone</a></p>\n<h3>Best Crystal to Wear Daily</h3>\n<p><p>For brave daily freedom, Amazonite is the stone to wear. Associated with honest communication and calm courage, it carries the heart-and-throat energy that helps you speak your own truth kindly but clearly. Worn as a bracelet or pendant, it can act as a quiet daily reminder that independence includes the freedom to be honest about what you actually want, and that real freedom rarely requires you to be harsh to be clear.</p></p>\n<p><em>Amazonite</em> — best for brave daily freedom. <a href=\"/gemstone/amazonite-meaning/\">Read full Amazonite meaning</a> · <a href=\"/product-category/amazonite-crystals/\">Shop Amazonite</a></p>\n<h3>How to Use These Crystals When You See 151</h3>\n<p><p>When 151 catches your eye, try a small ritual rather than a complicated one. Hold your chosen crystal in your receiving hand and take three slow breaths, letting your shoulders drop on each exhale. Then set a single intention for the day — one choice you will make from your own center, whether that is speaking a preference, declining something that does not fit, or taking the first step on something that is yours. You might carry the stone in a pocket or wear it as jewelry so it nudges you back to that intention when old habits resurface. At day's end, hold the crystal again and notice, without judgment, whether your choices felt like your own.</p></p>\n\n<h2>Why Do You Keep Seeing 151?</h2>\n<p><p>Repeating numbers tend to show up most when something inside you is already shifting — often before your conscious mind has named it. If 151 keeps appearing, a few readings are worth considering.</p>\n<p>First, it may simply be a mindfulness marker. The mind is pattern-seeking, and once 151 has caught your attention you will start noticing it in places you would otherwise overlook. That is not a flaw; it is the mechanism. The number becomes a recurring bell, pulling you back to a question worth sitting with: am I leading my own life right now, or am I on a path someone else charted?</p>\n<p>Second, 151 often surfaces at transition points — a quiet identity change rather than a loud one. You may be on the edge of claiming a preference, ending an arrangement that no longer fits, or beginning something that finally feels like yours. The mirror of two 1s suggests an inner consistency forming: who you are becoming is starting to match who you have quietly been. Rather than reading the number as a fixed omen, you might treat it as a confirmation that the direction you have been sensing is worth trusting. Pair it with honest self-reflection, and let it point you back to choices you can genuinely own.</p></p>\n\n<h2>What to Do When You See 151</h2>\n<p><p>Working with 151 is less about a single dramatic move and more about a sequence of self-directed ones. Consider these steps:</p>\n<ul>\n<li><strong>Name one area where you have outsourced your authority.</strong> Pick the first thing that comes to mind — a decision you keep deferring, a choice you are waiting to be told to make. That is your starting point.</li>\n<li><strong>Take one small, owned action this week.</strong> Independence is built through practice, not declaration. Make a modest choice that is clearly yours, and notice how it feels to move from your own center.</li>\n<li><strong>Carry a supporting crystal.</strong> Hold Carnelian, Tiger Eye, or your chosen stone for three breaths before the action. Use it as a physical anchor for the intention, not a guarantee of any outcome.</li>\n<li><strong>Add a moment of reflection.</strong> Since 151 reduces to 7, give the wisdom layer its due. At the end of the day, ask whether your choice felt truly yours — and what you learned about your own judgment.</li>\n<li><strong>Let freedom follow consistency.</strong> The two 1s suggest that real freedom grows from a self that is consistent. Keep making owned choices, and let the freedom of the 5 expand naturally from there.</li>\n</ul></p>\n\n<h2>Frequently Asked Questions</h2>\n<h3>What is 151 trying to tell me?</h3>\n<p>Many traditions read 151 as a nudge toward mirrored independence — the idea that your inner self-leadership is ready to show up in how you actually live. It is often read as an invitation to claim your own direction, make a self-directed choice you have been delaying, and trust your judgment rather than waiting for permission.</p>\n\n<h3>What does 151 mean spiritually?</h3>\n<p>Spiritually, 151 blends the independence of two 1s with the freedom of a central 5, then reduces to 7 (1+5+1), adding a layer of inner wisdom. Together these point to a freedom that is grounded in reflection rather than impulse — self-leadership that has been tested and earned.</p>\n\n<h3>What is the best crystal for 151?</h3>\n<p>Carnelian is widely chosen as the best overall crystal for 151, thanks to its traditional association with courage, motivation, and initiative — qualities that match the self-led energy of the number. Tiger Eye and Sunstone are also commonly paired with 151 for grounding and radiant confidence respectively.</p>\n\n<h3>How do I use crystals with angel number 151?</h3>\n<p>Hold your chosen crystal, take three slow breaths, and set one intention for the day — a single choice you will make from your own center. Carry or wear the stone as a reminder. You can use it as a mindfulness anchor; it is not meant to guarantee any specific outcome.</p>\n\n<h3>Are angel numbers scientifically proven?</h3>\n<p>No. Angel numbers are part of spiritual and numerological traditions, not scientifically validated phenomena. Their value for many people is symbolic and reflective — as recurring prompts for self-awareness — rather than factual predictions. They are not a substitute for professional medical, financial, or psychological advice.</p>\n\n<h3>Is 151 a good or bad sign?</h3>\n<p>151 is generally read as a positive or neutral sign pointing toward independence and freedom, but it is not inherently lucky or unlucky. Numbers like this are best understood as invitations to reflect and act, not as fixed omens of good or bad fortune.</p>\n\n<p class=\"gentle-note\"><em>Crystal and angel number meanings are based on spiritual traditions, symbolism, and personal mindfulness practices. They are not a substitute for medical, financial, or professional advice.</em></p>\n\n<h2>Related Angel Numbers</h2>\n<ul>\n<li><a href=\"/515-angel-number-meaning/\">515 Angel Number</a> — Mirrored Change toward Independence / Liberating Fresh Start</li>\n<li><a href=\"/115-angel-number-meaning/\">115 Angel Number</a> — New Creative Start / Manifested Expression</li>\n<li><a href=\"/1551-angel-number-meaning/\">1551 Angel Number</a> — Mirrored Change / Reflected Transformation</li>\n</ul>\n<p><p>The 151 angel number carries a clear, mirrored message: your self-leadership is ready to become lived freedom. Whether it shows up on a clock, a receipt, or a plate you pass in traffic, you can read it as a gentle invitation to claim your own direction, make one owned choice, and trust the wisdom that comes from acting on your own judgment. Pair it with a crystal that grounds you, a moment of honest reflection, and the willingness to let your independence be seen. The path it points to is yours to walk.</p></p>",
  "images": {
    "hero": {
      "file": "assets/images/generated/9.angel-numbers/151/151-hero.webp",
      "source_type": "number-hero",
      "alt": "A spiritual artwork for angel number 151: the digits \"151\" rendered as a luminous central focal point in elegant glowing golden typography radiating warm light, surrounded by delicate arrangements of Carnelian, Citrine, Sunstone crystals and subtle sacred geometry, ethereal cosmic background in deep indigo and gold tones, floating light particles, premium editorial spiritual design"
    }
  }
}